pancritic/__init__.py
pancritic/__main__.py
pancritic/filters.py
pancritic/main.py
pancritic/template.py
pancritic/version.py
pancritic-0.3.2.dist-info/LICENSE
pancritic-0.3.2.dist-info/METADATA
pancritic-0.3.2.dist-info/WHEEL
pancritic-0.3.2.dist-info/entry_points.txt
pancritic-0.3.2.dist-info/top_level.txt
pancritic-0.3.2.dist-info/RECORD
