Metadata-Version: 2.1
Name: pancritic
Version: 0.3.2
Summary: CriticMarkdup parser with optional pandoc backend
Home-page: https://github.com/ickc/pancritic
Author: Kolen Cheung
Author-email: christian.kolen@gmail.com
License: BSD-3-Clause
Keywords: pandoc panflute markdown latex html criticmarkup
Platform: UNKNOWN
Classifier: Development Status :: 4 - Beta
Classifier: Environment :: Console
Classifier: Intended Audience :: End Users/Desktop
Classifier: Intended Audience :: Developers
Classifier: Topic :: Software Development :: Build Tools
Classifier: Topic :: Text Processing :: Filters
Classifier: License :: OSI Approved :: GNU General Public License v3 (GPLv3)
Classifier: Programming Language :: Python :: 2
Classifier: Programming Language :: Python :: 2.7
Classifier: Programming Language :: Python :: 3
Classifier: Programming Language :: Python :: 3.5
Classifier: Programming Language :: Python :: 3.6
Classifier: Programming Language :: Python :: 3.7
Classifier: Programming Language :: Python :: 3.8
Classifier: Programming Language :: Python :: 3.9
Classifier: Programming Language :: Python :: Implementation :: CPython
Classifier: Programming Language :: Python :: Implementation :: PyPy
Provides-Extra: dev
Requires-Dist: check-manifest ; extra == 'dev'
Provides-Extra: test
Requires-Dist: requests ; extra == 'test'
Requires-Dist: pep8 ; extra == 'test'
Requires-Dist: pytest ; extra == 'test'
Requires-Dist: pytest-cov ; extra == 'test'
Requires-Dist: coverage ; extra == 'test'
Requires-Dist: coveralls ; extra == 'test'
Requires-Dist: markdown ; extra == 'test'
Requires-Dist: markdown2 ; extra == 'test'
Requires-Dist: panflute ; extra == 'test'
Requires-Dist: pypandoc ; extra == 'test'
